UC_Quantum_Lab/__init__.py
UC_Quantum_Lab/_src.py
UC_Quantum_Lab/commands.py
UC_Quantum_Lab/layout.py
U_Cincy_quantum_tools-0.1.4.dist-info/LICENSE
U_Cincy_quantum_tools-0.1.4.dist-info/METADATA
U_Cincy_quantum_tools-0.1.4.dist-info/WHEEL
U_Cincy_quantum_tools-0.1.4.dist-info/top_level.txt
U_Cincy_quantum_tools-0.1.4.dist-info/RECORD
